{
    "paper_index": 23,
    "sections": [
        {
            "section_index": 0,
            "section_ref": "23:0",
            "pars": [
                {
                    "par_ref": "23:0.1",
                    "par_pageref": "256.1",
                    "par_content": "单独使者们，是共同创造者即无限之灵所属的贴身性及宇宙性团队；他们是无限之灵所属之高等人格体中的首个高级类别。他们代表着无限之灵在单独运作方面的最初创造性行动，目的在于创生出众多单独的人格性属灵。上父和上子都不直接参与这一伟大的属灵化过程。"
                },
                {
                    "par_ref": "23:0.2",
                    "par_pageref": "256.2",
                    "par_content": "这些属灵性使者们在一次单一的创造过程中得以人格化，而且其数目是固定的。虽然我在目前执行的这个使命中，就有一位这样的非凡存有与我相伴，但我却并不知道，在由众多宇宙所组成的宇宙中，一共有多少这样的人格体存在着。我只是不时地获悉，在我们超级宇宙的管辖范围内，有多少拥有注册记录而暂时运作着。从最近的尤沃萨(Uversa)报告中，我注意到，此时将近有7，690万亿个单独使者运作于奥温顿(Orvonton)的界域之内；而我猜测，这个数目还远少于其总数的七分之一。"
                }
            ]
        },
        {
            "section_index": 1,
            "section_ref": "23:1",
            "section_title": "1. 单独使者的本质与来源",
            "pars": [
                {
                    "par_ref": "23:1.1",
                    "par_pageref": "256.3",
                    "par_content": "紧随着七个哈沃纳(Havona)环路之灵的创造，无限之灵便创生了庞大的单独使者团队。除去天堂和哈沃纳众环路以外，宇宙创造物中没有任何部分是先存于单独使者的；他们从几近永恒之时起，就已在整个大宇宙中运作了。他们对于无限之灵用以向时空广袤造物进行自我展现及与之亲身接触的神性手段来说，是最为基本的。"
                },
                {
                    "par_ref": "23:1.2",
                    "par_pageref": "256.4",
                    "par_content": "虽然这些使者们从几近永恒之时起即已存在，但他们却都会意识到一个自我的开端。他们会意识到时间，且是无限之灵所属创造物中具有这种时间意识的最早一类。他们是一些在时间中得以人格化、在空间中得以灵性化的、无限之灵的头生受造物。"
                },
                {
                    "par_ref": "23:1.3",
                    "par_pageref": "256.5",
                    "par_content": "这些单独性之灵，早在时间之初，便作为成熟且具完美禀赋的属灵性存有而出现了。他们都是同等的，没有任何基于个体差异而产生的等级或细分。他们的分类，完全是基于其不时所被委派工作之类型。"
                },
                {
                    "par_ref": "23:1.4",
                    "par_pageref": "256.6",
                    "par_content": "凡人们作为几近物质性的存有，在各个空间世界上启程，并朝向各伟大中心而向内扬升；而这些单独性之灵，则由万物之中心出发，渴望被委派到遥远的造物，甚至是到众多最外地方宇宙所属的单个世界，乃至到更远之外。"
                },
                {
                    "par_ref": "23:1.5",
                    "par_pageref": "256.7",
                    "par_content": "尽管被命名为单独使者，但他们却并不是孤寂之灵，只因为他们确实喜欢单独地工作。他们是所有造物中唯一能真正乐于单独存在的存有，虽然他们也同样乐于与少数几类他们能与之友善往来的宇宙智能存有合作。"
                },
                {
                    "par_ref": "23:1.6",
                    "par_pageref": "257.1",
                    "par_content": "单独使者们在其服务方面并非是孤立的；他们不断与所有造物中的大量智能存有保持接触，因为他们能“聆听”到他们所旅居领域的所有广播。他们也能与其自身邻近团队的成员、亦即那些在同一超级宇宙中做着同类工作的存有们相互交流。他们原本也能与其同类的其他成员们交流，但七个主位之灵所形成的理事会已指示过他们不要这样做，而他们是一个忠诚的群体；他们不会违反或失职。还不曾有过一个单独使者陷入黑暗的记录。"
                },
                {
                    "par_ref": "23:1.7",
                    "par_pageref": "257.2",
                    "par_content": "单独使者与宇宙力量主管者们一样，是属于少数几类全域运作的存有，他们可免于各时空法庭所发出的逮捕或拘押。他们无法被传讯去出现在任何个体之前，除了七个主位之灵以外，但在主宇宙的所有历史记载中，该天堂理事会还从未被要求去裁决一个有关单独使者的案例。"
                },
                {
                    "par_ref": "23:1.8",
                    "par_pageref": "257.3",
                    "par_content": "这些有着单独性委派的使者们，是源自于第三本源与中心的受造存有中一支可靠自主、多才多艺、彻底灵性和广泛亲和的群体。他们是依照居于中央天堂岛、并在各地方宇宙总部有所体现的无限之灵的授权而运作。他们是发源于无限之灵的直接回路之持久分担者，即使是当他们在各地方宇宙母灵的直接影响下，在各个地方造物中运作之时。"
                },
                {
                    "par_ref": "23:1.9",
                    "par_pageref": "257.4",
                    "par_content": "单独使者们为何必须要单独地穿行和工作，存在着一个技术上的原因。在短期静止之时，他们能以群体的方式合作，但当这样在一起的时候，他们就会被完全切断了来自其天堂回路的指导和支持；他们就被完全地隔离了。当在穿行时，或在空间回路及时间环流中操作时，假如这类中的两个或是更多个非常接近，那么这两个或是全部便会被抛离出与各种高等环流力的联络。正如你们用形象化的话语所描述的，他们是“被短路”了。因此，在他们自身当中，固有着一种自动示警能力，一种警示信号，它能够准确无误地运作，以告知他们正在临近的冲突，并可靠地令他们有效地保持分离状态，从而不去干扰他们适当而有效的运作。他们也具有一些内在自觉的能力，以侦测和指示出激发性三一之灵和神性思想调整者的临近。"
                },
                {
                    "par_ref": "23:1.10",
                    "par_pageref": "257.5",
                    "par_content": "这些使者们并不具有人格扩展或复制之能力，但实际上，没有任何宇宙工作是他们所无法参与的，以及无法对之做出必要有用之贡献的。特别是对于那些涉及宇宙事务管理的存有们来说，他们极大节省了时间；他们协助着我们从最高等至最低等的所有群体。"
                }
            ]
        },
        {
            "section_index": 2,
            "section_ref": "23:2",
            "section_title": "2. 单独使者的委派",
            "pars": [
                {
                    "par_ref": "23:2.1",
                    "par_pageref": "257.6",
                    "par_content": "单独使者们并非永久地被配属给任何单个或集体的天界人格体们。他们总是因委派而在职，在这样的服务中，他们在其所派领域主管者的直接监督下工作，而在他们自身中间，则没有任何类型的组织或管理机构；他们是*单独的*使者。"
                },
                {
                    "par_ref": "23:2.2",
                    "par_pageref": "258.1",
                    "par_content": "单独使者们，由无限之灵分配到以下七个服务分类中："
                },
                {
                    "par_ref": "23:2.3",
                    "par_pageref": "258.2",
                    "par_content": "1. 天堂三位一体之使者。"
                },
                {
                    "par_ref": "23:2.4",
                    "par_pageref": "258.3",
                    "par_content": "2. 哈沃纳(Havona)环路之使者。"
                },
                {
                    "par_ref": "23:2.5",
                    "par_pageref": "258.4",
                    "par_content": "3. 超级宇宙之使者。"
                },
                {
                    "par_ref": "23:2.6",
                    "par_pageref": "258.5",
                    "par_content": "4. 地方宇宙之使者。"
                },
                {
                    "par_ref": "23:2.7",
                    "par_pageref": "258.6",
                    "par_content": "5. 无定向委派之探索者。"
                },
                {
                    "par_ref": "23:2.8",
                    "par_pageref": "258.7",
                    "par_content": "6. 特殊委派之大使及密使。"
                },
                {
                    "par_ref": "23:2.9",
                    "par_pageref": "258.8",
                    "par_content": "7. 真理之启示者。"
                },
                {
                    "par_ref": "23:2.10",
                    "par_pageref": "258.9",
                    "par_content": "这些属灵性使者们，在各种意义上都可从某一种服务类型转换成另一服务类型；这样的转换是不断发生的。并不存在什么分开类别的单独使者；他们在灵性上都是相似的，在各种意义上都是同等的。尽管他们一般以编号来命名，但他们都凭各自的名字而为无限之灵所知。对于我们其余存有来说，他们则凭名字或其现行委派中的指定编号而被了解。"
                },
                {
                    "par_ref": "23:2.11",
                    "par_pageref": "258.10",
                    "par_content": "1. *天堂三位一体之使者。*我未被允许启示太多关于配属给三位一体的使者群体之工作。他们是一些值得神灵们信赖的秘密服务者，当被委托以涉及诸神之未透露策略及未来安排的特殊消息时，他们从未被了解到去泄露一个秘密，或是有负于寄予其类别身上的信任。与这相关的所有这一切，不是对其完美性表示夸耀，而是要指出神灵们能够且确实创造出了*完美的存有。*"
                },
                {
                    "par_ref": "23:2.12",
                    "par_pageref": "258.11",
                    "par_content": "玉苒厦(Urantia)所发生的混乱和动荡，并不表明天堂支配者们缺乏兴趣或能力去以不同方式管理事务。造物主们有着充分的能力，去让玉苒厦成为一个名副其实的乐园，但这样一个伊甸园，并不会有助于那些坚强、高贵及富有经验之品格的发展，而这些品格正是诸神如此坚定不移地在你们世界上以困境为砧、以痛苦为锤着力锻造出来的。你们的忧愁和悲伤，你们的苦难和失意，正是神性计划在你们星球上的一个组成部分，恰如在中央完美宇宙的世界上，万物之精巧完美与无限适应符合其至高性目的一样。"
                },
                {
                    "par_ref": "23:2.13",
                    "par_pageref": "258.12",
                    "par_content": "2. *哈沃纳(Havona)环路之使者。*在整个扬升生涯中，你们会模糊地、但却又越来越多地能察觉到单独使者们的存在，但直到你们到达哈沃纳之后，你们才能够准确无误地辨识出他们。你们会当面见到的第一批单独使者，将会是那些哈沃纳环路之使者。"
                },
                {
                    "par_ref": "23:2.14",
                    "par_pageref": "258.13",
                    "par_content": "单独使者们与哈沃纳(Havona)各世界的原住民之间，享受着一种特殊的关系。这些在彼此合作时职能受限的使者们，与哈沃纳原住民们却可以而且确实有着一种非常紧密的个体交流。但是，要想把这些神性完美的存有与那样一些近乎超越性的人格体之间的心灵接触所引发的极大快事传递给人类心智，则是完全不可能的。"
                },
                {
                    "par_ref": "23:2.15",
                    "par_pageref": "259.1",
                    "par_content": "3. *超级宇宙之使者。*亘古常在者们，亦即那些有着三位一体来源、主掌着七个超级宇宙天命的人格体，那些有着神性权力和管理智慧的三位一组，被充足地配备着单独使者。只有通过这一类型的使者们，某一个超级宇宙的这些三位联合式支配者们，才能直接与另一超级宇宙的同类支配者们进行个别联络。或许，除开激发性三一之灵以外，单独使者们是灵性智能存有中能够从一个超级宇宙总部直接派到另一个超级宇宙总部的唯一可用类型。所有其他人格体，要想实现这种跋涉，则必须取道于哈沃纳(Havona)，以及各主位之灵的执行世界。"
                },
                {
                    "par_ref": "23:2.16",
                    "par_pageref": "259.2",
                    "par_content": "有某些类信息，是不能通过引力使者、反射性或广播来获得的。而当亘古常在者们一定要知道这些事情时，他们必须要派遣一名单独使者前往信息之源。早在玉苒厦(Urantia)上出现生命的很久以前，目前伴随我的这位单独使者，曾因一个使命而从尤沃萨(Uversa)被派往中央宇宙，他从奥温顿(Orvonton)的名册中消失了几近一百万年之久，但最终携带所需信息准时归来。"
                },
                {
                    "par_ref": "23:2.17",
                    "par_pageref": "259.3",
                    "par_content": "单独使者们在各个超级宇宙中的服务，是没有限制的；他们既可以高级法庭执行者的身份运作，也可以该域福祉所需之信息搜集者的身份运作。在所有超级造物中，他们特别乐于在奥温顿(Orvonton)超级宇宙中服务，因为在这里有着最为迫切的需要，而可完成英雄业绩之机会也大大增加了。在更为需要的领域中，我们都享受着一种更为充实的运作所带来的满足感。"
                },
                {
                    "par_ref": "23:2.18",
                    "par_pageref": "259.4",
                    "par_content": "4. *地方宇宙之使者。*在地方宇宙的众多服务部门中，单独使者们的运作是没有任何限制的。他们是地方宇宙母灵之动机和意图的忠诚启示者，虽然他们也在掌权的主位之子的全面管辖之下。这对于运作于一个地方宇宙中的所有单独使者来说，都是成立的，不管他是从宇宙总部直接出行，抑或是暂时地与星座之父、系统君主或行星君王一起运作。在一个造物之子被提升为其宇宙的主权支配者，因而将所有权力集于他手之前，这些地方宇宙单独使者们，在亘古常在者们总的指导下运作着，并直接对后者之常驻代表联合常在者们负责。"
                },
                {
                    "par_ref": "23:2.19",
                    "par_pageref": "259.5",
                    "par_content": "5.* 无定向委派之探索者。*当单独使者之后备团队有所超编时，从七个至高性力量主管者之一，便会发出一个召唤，以征集探索志愿者；而志愿者从未匮乏过，因为他们都乐于被派遣出去，作为自由自在的探索者们，去体验那种发现新宇宙世界之组织核心的刺激感。"
                },
                {
                    "par_ref": "23:2.20",
                    "par_pageref": "259.6",
                    "par_content": "他们前往去探究由各域之空间推究者们所提供的线索。毫无疑问，天堂神灵们知道这些未被发现的空间能量系统之存在，但他们永远不会泄露此类信息。如果单独使者们不曾探索和标明这些新的组织性能量中心，那么此类现象就甚至会被临近各域的智能存有们所忽视。单独使者们作为一个种类，对于引力极为敏感；相应地，他们能时常侦测出非常小的暗行星之可能存在，而这些世界也正是最适合于生命实验的。"
                },
                {
                    "par_ref": "23:2.21",
                    "par_pageref": "260.1",
                    "par_content": "这些有着非定向委派的使者与探险者们，巡行在主宇宙中。他们不断外出至整个外部空间的未明区域中，进行着探索之旅。对于我们所拥有的关于外部空间各域中诸多事务的大量知识，我们要归功于单独使者们的探索，因为他们经常与天界的天文学者们一同工作和研究。"
                },
                {
                    "par_ref": "23:2.22",
                    "par_pageref": "260.2",
                    "par_content": "6.* 特殊委派之大使及密使。*处于同一超级宇宙内的各地方宇宙之间，按惯例要互相交换一些选自其本地子民类别的大使。但为了避免延误，单独使者常被请求作为大使，从一个地方造物前往另一个，去代表一域，并将之介绍给另一域。例如：当一个新的居住性领域得以发现时，或许结果是它在空间中是如此遥远，以至于在一个由炽天使所裹挟的大使能到达该遥远宇宙之前，一段漫长的时间已过去了。一个由炽天使所裹挟之存有，在你们的一秒时间内，不可能超过899，370公里的速度。巨大星体、逆流和绕道，以及引力突变等，往往都会令这一速度减慢，以致在一个漫长的旅程中，速度平均只会达到每秒885，000公里。"
                },
                {
                    "par_ref": "23:2.23",
                    "par_pageref": "260.3",
                    "par_content": "当情况发展到需要一个本地大使花费成百上千年去往一个遥远地方宇宙之时，一个单独使者通常会被请求立即前往那里，去作为一个临时大使而运作。单独使者们能在极短的规程内前去，虽然不像引力使者们那样完全不依赖于时空，但也几近如此了。在一些其它情况下，他们也作为特殊委派之密使而服务。"
                },
                {
                    "par_ref": "23:2.24",
                    "par_pageref": "260.4",
                    "par_content": "7.* 真理之启示者。*单独使者们把启示真理之委派，当作是对其类别的最高信赖。他们时常以此种身份而运作，从各个超级宇宙去到空间中的单个行星。他们常被配属到一些考察团，它们受派去将真理之启示扩展到各个世界和系统。"
                }
            ]
        },
        {
            "section_index": 3,
            "section_ref": "23:3",
            "section_title": "3. 单独使者的时空服务",
            "pars": [
                {
                    "par_ref": "23:3.1",
                    "par_pageref": "260.5",
                    "par_content": "当不适宜于利用广播服务和反射性机制来进行紧急重要信息的快速传递时，单独使者们是所有各域中完美而值得信赖的可用人格体中最为高等的类型。他们服务于种类繁多的各样委派，旨在帮助各域的灵性及物质性存有，尤其是在那些涉及时间因素的领域当中。在派往超级宇宙各域之服务部门的所有类别当中，他们是最高等和最多能的人格化存有，他们能几近达至无视时空的程度。"
                },
                {
                    "par_ref": "23:3.2",
                    "par_pageref": "260.6",
                    "par_content": "宇宙中充满着一些将引力用作运送用途的属灵体；他们能够在任意时间去往任何地点 -- 但他们并非是人格体。某些其他的引力性穿越者是人格性存有，例如引力使者和超越性记录者们，但他们对于超级宇宙和地方宇宙的管理者们来说是不可用的。众多世界充满了天使和人类，以及其他极具人格性的存有，但他们都受到时间和空间的阻滞：按你们世界的距离和时间单位计算，大多数非天使裹挟性存有的极限速度是299，790公里/秒；中道受造物和某些其他受造物可以而且经常确实达到双倍速度 -- 即599，580公里/秒；而炽天使和一些其他存有，可以以三倍于此的速度穿越空间，即大约899，370公里/秒。不过，除了单独使者而外，再没有一种运送性或者使者性人格体，能够以介乎引力性穿越者的瞬时性速度与炽天使的稍缓速度中间的速度来运行。"
                },
                {
                    "par_ref": "23:3.3",
                    "par_pageref": "261.1",
                    "par_content": "因此，在那些人格体之于委派之达成十分必要的情况下，以及在那些需要避免因派遣其他任何现成类型的人格性使者而造成时间损失的情况下，单独使者们通常被用于派遣及服务。他们是唯一能够与大宇宙的综合性宇宙环流相同步的明确人格化存有。他们在空间中的穿行速度是可变的，这取决于众多的干扰性影响，但记录表明，在前往履行这一使命的旅程中，我随身的单独使者是以1，354，458，739，000公里/秒的速度行进着。"
                },
                {
                    "par_ref": "23:3.4",
                    "par_pageref": "261.2",
                    "par_content": "去向物质性类型的心智解释一个属灵体何以能是一个真正的人格体，同时又能以如此惊人的速度穿越空间，这完全超出了我的能力之外。但正是这些单独使者，确实是以这样不可思议的速度往来于玉苒厦(Urantia)；事实上，如果事实不是如此，那么整个宇宙管理体制将会被极大剥夺了其人格性要素。"
                },
                {
                    "par_ref": "23:3.5",
                    "par_pageref": "261.3",
                    "par_content": "单独使者们能够在整个遥远的空间区域，亦即在那些未被包含在大宇宙既成回路内的各域，起到紧急通讯线路的作用。当一个单独使者以此方式运作时，按照玉苒厦(Urantia)天文学家们估算星际距离的方式来推展，他能够通过空间传输一个信息或者发送一个脉冲，给一个远隔一百光年处的同类使者。"
                },
                {
                    "par_ref": "23:3.6",
                    "par_pageref": "261.4",
                    "par_content": "在与我们合作处理超级宇宙事务的无数存有当中，没有任何其他存有会在实用有益性和省时援助性方面更为重要了。在空间宇宙中，我们必须考虑到时间的阻滞；因而就有了单独使者们的重要服务，他们利用其人格性交流特权，可以几乎不受空间的制约，又凭借其惊人的传送速度，而几乎不受时间的制约。"
                },
                {
                    "par_ref": "23:3.7",
                    "par_pageref": "261.5",
                    "par_content": "我很为难于向玉苒厦(Urantia)凡人们解释，单独使者们何以不具形体，然却仍具有真实而明确的人格本体。虽然他们并没有那种为人格本体所自然伴随的形体，但他们却确实具有一种灵性的临在，而这是所有高等灵性存有们所能够分辨的。单独使者们是唯一的这样一类存有，他们似乎具有一个无形属灵体几近一切的优点，而又有成熟人格体的所有特权。他们是真正的人格，而又具有非人格属灵显现物的几乎所有属性。"
                },
                {
                    "par_ref": "23:3.8",
                    "par_pageref": "261.6",
                    "par_content": "在七个超级宇宙中，每样易令任何受造物从时空阻碍中的解脱能力得以增加之事物，通常会相称地缩减其人格性特权，但并不总是这样。而单独使者便是这一普遍规律的一个例外。在其活动中，他们在灵性表达、神性服务、人格性侍奉和宇宙性交流等所有各类无限手段之运用方面，几乎是无所限制的。如果你们能根据我在宇宙管理中的经历来看待这些非凡的存有，你们将会理解，如果没有其多能的协作，那么去协调众多超级宇宙事务将会是多么困难。"
                },
                {
                    "par_ref": "23:3.9",
                    "par_pageref": "262.1",
                    "par_content": "无论宇宙会扩展到什么程度，可能永远都不会再有更多的单独使者被创造出来了。随着众多宇宙的发展，新增添的管理工作必须不断地由其他类型的灵性侍奉者及那些出身于这些新造物的存有们来承担，诸如由主位之子和地方宇宙母灵所创的一些受造物。"
                }
            ]
        },
        {
            "section_index": 4,
            "section_ref": "23:4",
            "section_title": "4. 单独使者的特别侍奉",
            "pars": [
                {
                    "par_ref": "23:4.1",
                    "par_pageref": "262.2",
                    "par_content": "单独使者们似乎是所有类型的属灵性存有之人格性协调者。他们的侍奉有助于令广袤灵性世界的所有人格体和谐相处。他们对于在所有属灵性存有身上的群体认同意识之发展贡献颇多。每一类型的存有都由一些特定类别的单独使者们所服务着，后者会培养这些存有的这样一种能力，以去与所有其他类型和层次的存有们相互理解，相互友善，无论彼此有多么不同。"
                },
                {
                    "par_ref": "23:4.2",
                    "par_pageref": "262.3",
                    "par_content": "单独使者们表现出这样一种惊人的能力，去协调所有类型和层次的有限人格体 -- 甚至去与主宇宙总控制者们的绝限性体系相接触 --以致我们当中有些在猜想，无限之灵对这些单独使者们的创造，在某种方式上与共同行动者对至高兼终极性心智的赐与相关。"
                },
                {
                    "par_ref": "23:4.3",
                    "par_pageref": "262.4",
                    "par_content": "当一个终局者与一个天堂居民合作，进行一个“时间性兼永恒性之子”的三一化 -- 亦即一个牵涉到至高兼终极者之未明心智潜能的事务 -- 当这样一个尚未归类的人格体被派往代理者之都，此时便总会有一个单独使者（此种神灵心智之赐与所形成的一种猜想的人格性反响），被派遣作为该受造物所三一化之子的守护者和友伴。这个使者伴同这位新天命之子来到其委派的世界，就此便永不再离开代理者之都。当一个单独使者由此而与一个时间性兼永恒性之子的天命关联起来时，他便被永远地转入到主宇宙设计者的单独监管之下。这样一种非凡之组合的未来如何，我们无从知晓。很久以来，这些独特人格体们的伙伴关系在代理者之都上持续地集聚着，但还没有单一的一对曾从那儿出去过。"
                },
                {
                    "par_ref": "23:4.4",
                    "par_pageref": "262.5",
                    "par_content": "单独使者们有着固定的数目，但天命之子的三一化明显却是一种不受限制之技术。由于每一个三一化天命之子已被指派了一个单独使者，在我们看来，在遥远未来的某一个时刻，单独使者们的配给可能会开始枯竭。谁将会来接替他们在大宇宙中的工作？是不是他们的服务将会被激发性三一之灵中的某些新发展个体所承担？在某个遥远的未来时期，是不是大宇宙将更近乎由具备三位一体来源之存有所管理，而具有单一和双重来源的受造物们则将不断移入到外部空间各域？如果使者们回到其先前的服务团队，那些天命之子是不是也会伴同他们？当单独使者们的配给都被作为这些天命之子的守护者和友伴吸收之后，是不是终局者与天堂-哈沃纳者之间的三一化过程将告终止？是不是我们所有这些能干的单独使者们，都将被集中到代理者之都？是不是这些非凡的属灵性人格体将会永恒地与这些带有未知天命的三一化之子相伴随？这些聚集在代理者之都的搭档们，都是处于主宇宙设计者们这样一些强大神秘之存有的专门主管之下，对于这样一个事实，我们应当赋予它以什么样的重要意义？许多这类相似的问题，我们会问我们自己，也会问众多其他类别的天界存有，但我们并不知道答案。"
                },
                {
                    "par_ref": "23:4.5",
                    "par_pageref": "263.1",
                    "par_content": "这一事务，与宇宙管理中许多类似事件一起，清楚地表明，大宇宙乃至哈沃纳(Havona)和天堂之属员，正在经历着一个确定的重组，该重组是与目前发生于整个外部空间领域内的巨大能量演化相互协调、相互关联的。"
                },
                {
                    "par_ref": "23:4.6",
                    "par_pageref": "263.2",
                    "par_content": "我们倾向于相信，永恒之未来将会见证一些宇宙演化现象，它们将远超所有那些在永恒之过去所经历过的。我们怀着热切的兴趣和日益高涨的期待，甚至你们也应同样，期盼着这些巨大的冒险。"
                },
                {
                    "par_ref": "23:4.7",
                    "par_pageref": "263.3",
                    "par_content": "[由一位来自尤沃萨(Uversa)的神性顾问所呈献。]"
                }
            ]
        }
    ],
    "footnotes": [],
    "paper_title": "单独使者",
    "author": "神性顾问"
}